pipstat
