Metadata-Version: 1.1
Name: pipstat
Version: 0.2.1
Summary: Get download counts for PyPI packages from the command line
Home-page: https://github.com/sloria/pipstat
Author: Steven Loria
Author-email: sloria1@gmail.com
License: Copyright 2014 Steven Loria
